<?xml version="1.0"?>
<CustomerLoansList xmlns="http://Customer360/XSD/CustomerLoans.xsd">
	<CustomerLoans>
		<cust_id>123</cust_id>
		<CreditCards>
			<CreditCard>
				<cust_id>123</cust_id>
				<cc_type>VISA</cc_type>
				<cc_number>33-xx-567</cc_number>
				<cc_balance>15000.00</cc_balance>
				<cc_interest_rate>19.0</cc_interest_rate>
			</CreditCard>
			<CreditCard>
				<cust_id>123</cust_id>
				<cc_type>MC</cc_type>
				<cc_number>123456-cc-12</cc_number>
				<cc_balance>20000.00</cc_balance>
				<cc_interest_rate>18.5</cc_interest_rate>
			</CreditCard>
		</CreditCards>
		<CreditLines>
			<CreditLine>
				<cust_id>123</cust_id>
				<cl_acct_number>cl-123-xx-555</cl_acct_number>
				<cl_limit>30000.00</cl_limit>
				<cl_interest_rate>15.0</cl_interest_rate>
				<cl_balance>10000.00</cl_balance>
			</CreditLine>
		</CreditLines>
		<Mortgages>
			<Mortgage>
				<cust_id>123</cust_id>
				<mortgage_acct_num>mrt_0123-dd</mortgage_acct_num>
				<mortgage_value>250000.00</mortgage_value>
				<mortgage_paid>100000.00</mortgage_paid>
				<mortgage_type>Fixed</mortgage_type>
				<mortgage_end_year>2020</mortgage_end_year>
				<mortgage_interest_rate>5.5</mortgage_interest_rate>
			</Mortgage>
		</Mortgages>
	</CustomerLoans>
	<CustomerLoans>
		<cust_id>125</cust_id>
		<CreditCards>
			<CreditCard>
				<cust_id>125</cust_id>
				<cc_type>VISA</cc_type>
				<cc_number>33-xx-5699</cc_number>
				<cc_balance>10000.00</cc_balance>
				<cc_interest_rate>19.0</cc_interest_rate>
			</CreditCard>
		</CreditCards>
		<CreditLines>
			<CreditLine>
				<cust_id>125</cust_id>
				<cl_acct_number>cl-123-xx-555</cl_acct_number>
				<cl_limit>10000.00</cl_limit>
				<cl_interest_rate>15.0</cl_interest_rate>
				<cl_balance>200.00</cl_balance>
			</CreditLine>
		</CreditLines>
		<Mortgages>
			<Mortgage>
				<cust_id>125</cust_id>
				<mortgage_acct_num>mrt_0123-yy</mortgage_acct_num>
				<mortgage_value>300000.00</mortgage_value>
				<mortgage_paid>100000.00</mortgage_paid>
				<mortgage_type>Variable</mortgage_type>
				<mortgage_end_year>2030</mortgage_end_year>
				<mortgage_interest_rate>7.2</mortgage_interest_rate>
			</Mortgage>
	</Mortgages>
	</CustomerLoans>
</CustomerLoansList>

  